dingraia/DingTalk.py
dingraia/VERSION.py
dingraia/__init__.py
dingraia/__main__.py
dingraia/cache.py
dingraia/callback_handler.py
dingraia/config.py
dingraia/context.py
dingraia/element.py
dingraia/exceptions.py
dingraia/fool.py
dingraia/http_page.py
dingraia/lazy.py
dingraia/log.py
dingraia/signer.py
dingraia/vars.py
dingraia/verify.py
dingraia/event/__init__.py
dingraia/event/event.py
dingraia/event/message.py
dingraia/message/__init__.py
dingraia/message/chain.py
dingraia/message/element.py
dingraia/model/__init__.py
dingraia/module/__init__.py
dingraia/module/radio_done_callback.py
dingraia/saya/__init__.py
dingraia/saya/channel.py
dingraia/saya/context.py
dingraia/saya/builtins/__init__.py
dingraia/saya/builtins/broadcast/__init__.py
dingraia/saya/builtins/broadcast/schema.py
dingraia/tools/__init__.py
dingraia/tools/color_text.py
dingraia/tools/debug.py
dingraia/tools/timer.py
dingraia-2.0.9.dist-info/LICENSE
dingraia-2.0.9.dist-info/METADATA
dingraia-2.0.9.dist-info/WHEEL
dingraia-2.0.9.dist-info/top_level.txt
dingraia-2.0.9.dist-info/zip-safe
dingraia-2.0.9.dist-info/RECORD
