Metadata-Version: 2.1
Name: dingraia
Version: 2.0.9
Summary: A Dingtalk robot framework based on Python, supported http and stream mode.
Home-page: https://github.com/MeiHuaGuangShuo/Dingraia
Author: MeiHuaGuangShuo
Author-email: meihuaguangshuo@gmail.com
Requires-Python: >3.7
License-File: LICENSE
Requires-Dist: loguru
Requires-Dist: requests
Requires-Dist: aiohttp
Requires-Dist: pycryptodome
Requires-Dist: websockets
Requires-Dist: rich
Requires-Dist: deprecation
